MANIFEST.in
README.txt
setup.py
medialog/__init__.py
medialog.qrcode.egg-info/PKG-INFO
medialog.qrcode.egg-info/SOURCES.txt
medialog.qrcode.egg-info/dependency_links.txt
medialog.qrcode.egg-info/entry_points.txt
medialog.qrcode.egg-info/namespace_packages.txt
medialog.qrcode.egg-info/not-zip-safe
medialog.qrcode.egg-info/requires.txt
medialog.qrcode.egg-info/top_level.txt
medialog/qrcode/__init__.py
medialog/qrcode/behavior.py
medialog/qrcode/behaviors.zcml
medialog/qrcode/configure.zcml
medialog/qrcode/interfaces.py
medialog/qrcode/tests.py
medialog/qrcode/browser/__init__.py
medialog/qrcode/browser/configure.zcml
medialog/qrcode/browser/qrsummaryview.pt
medialog/qrcode/browser/qrviews.py
medialog/qrcode/portlets/__init__.py
medialog/qrcode/portlets/configure.zcml
medialog/qrcode/portlets/qrportlet.pt
medialog/qrcode/portlets/qrportlet.py
medialog/qrcode/profiles/default/browserlayer.xml
medialog/qrcode/profiles/default/metadata.xml
medialog/qrcode/profiles/default/portlets.xml
medialog/qrcode/viewlets/__init__.py
medialog/qrcode/viewlets/configure.zcml
medialog/qrcode/viewlets/document_qrrelateditems.pt
medialog/qrcode/viewlets/qrviewlet.pt
medialog/qrcode/viewlets/viewlets.py