Metadata-Version: 1.1
Name: medialog.qrcode
Version: 0.2
Summary: QRcode views and portlet for Plone.
Home-page: https://github.com/espenmn/medialog.qrcode/
Author: Espen Moe-Nilssen
Author-email: espen@medialog.no
License: GPL
Keywords: QRcode QR generator
Platform: UNKNOWN
Classifier: Framework :: Plone
Classifier: Programming Language :: Python
